[
    {
        "session_id": "005F5A1BB874BF14B06408B4C71D194E",
        "source": "路由仲裁测试0611评测明细20260616_f853ce69bad0439fb72f0aec1d649b7d_1781593870590",
        "timestamp": "2026-06-07 17:55:07",
        "historyDialogue": [
            "user: 你好，在吗？",
            "assistant: 您好，请问有什么可以帮您？",
            "user: 我要结清欠款。但我还款时要我之前手机号验证码",
            "assistant: 您在还款时需要验证当前绑定的手机号码，若需更换手机号接收验证码，可前往APP【我的】-【右上角小齿轮】-【安全中心】-【修改注册手机号】进行更新操作。如遇其他问题，可随时告知小马哦~"
        ],
        "query": "我是支付宝里面 哪里有更改手机号？",
        "current_agent": "闲聊",
        "router_reason": "【测试组】1. 连贯性：用户最新问题关于支付宝更改手机号，与历史对话中还款验证码接收问题相关，属于对话延续；2. 匹配度：用户问题涉及支付宝验证码接收，属于还款Agent职责中“支持的还款方式”及“反馈还款链接未成功接收”范畴，证据明确；",
        "router_agent": "还款",
        "human_note": "更改手机号应给逾期及app使用",
        "human_annotate_agent": "逾期及APP使用",
        "final_agent": "逾期及APP使用"
    }
]